sm_blueprint_lib/__init__.py
sm_blueprint_lib/blueprint.py
sm_blueprint_lib/body.py
sm_blueprint_lib/bounds.py
sm_blueprint_lib/constants.py
sm_blueprint_lib/icon.png
sm_blueprint_lib/id.py
sm_blueprint_lib/pos.py
sm_blueprint_lib/rot.py
sm_blueprint_lib/utils.py
sm_blueprint_lib/bases/__init__.py
sm_blueprint_lib/bases/controllers/__init__.py
sm_blueprint_lib/bases/controllers/basecontroller.py
sm_blueprint_lib/bases/controllers/baselogiccontroller.py
sm_blueprint_lib/bases/controllers/logicgatecontroller.py
sm_blueprint_lib/bases/controllers/sensorcontroller.py
sm_blueprint_lib/bases/controllers/timercontroller.py
sm_blueprint_lib/bases/joints/__init__.py
sm_blueprint_lib/bases/joints/basejoint.py
sm_blueprint_lib/bases/joints/basejointcontroller.py
sm_blueprint_lib/bases/joints/pistonjoint.py
sm_blueprint_lib/bases/joints/pistonjointcontroller.py
sm_blueprint_lib/bases/joints/suspensionjoint.py
sm_blueprint_lib/bases/joints/suspensionjointcontroller.py
sm_blueprint_lib/bases/parts/__init__.py
sm_blueprint_lib/bases/parts/baseboundablepart.py
sm_blueprint_lib/bases/parts/baseinteractablepart.py
sm_blueprint_lib/bases/parts/baselogicpart.py
sm_blueprint_lib/bases/parts/basepart.py
sm_blueprint_lib/blocks/__init__.py
sm_blueprint_lib/blocks/block.py
sm_blueprint_lib/parts/__init__.py
sm_blueprint_lib/parts/bearing.py
sm_blueprint_lib/parts/button.py
sm_blueprint_lib/parts/logicgate.py
sm_blueprint_lib/parts/piston.py
sm_blueprint_lib/parts/sensor.py
sm_blueprint_lib/parts/suspension.py
sm_blueprint_lib/parts/switch.py
sm_blueprint_lib/parts/timer.py
sm_blueprint_lib/prebuilds/__init__.py
sm_blueprint_lib/prebuilds/adder.py
sm_blueprint_lib/prebuilds/barrel_shifter.py
sm_blueprint_lib/prebuilds/clock40hz.py
sm_blueprint_lib/prebuilds/comparator.py
sm_blueprint_lib/prebuilds/counter.py
sm_blueprint_lib/prebuilds/decoder.py
sm_blueprint_lib/prebuilds/distance_sensor.py
sm_blueprint_lib/prebuilds/ram.py
sm_blueprint_lib/prebuilds/register.py
sm_blueprint_lib-0.0.17.dist-info/METADATA
sm_blueprint_lib-0.0.17.dist-info/WHEEL
sm_blueprint_lib-0.0.17.dist-info/licenses/LICENSE.txt
sm_blueprint_lib-0.0.17.dist-info/RECORD
