Metadata-Version: 2.4
Name: sm_blueprint_lib
Version: 0.0.17
Summary: Scrap Mechanic Library for Blueprint manipulation.
Project-URL: Homepage, https://github.com/MauriceTZ/sm_blueprint_lib
Project-URL: Issues, https://github.com/MauriceTZ/sm_blueprint_lib/issues
Author: niknal357
Author-email: Maurice <mauriciotorrez00@gmail.com>, lnventorsteve <dylanv60431@gmail.com>
License-Expression: MIT
License-File: LICENSE.txt
Classifier: Operating System :: OS Independent
Classifier: Programming Language :: Python :: 3
Requires-Python: >=3.8
Requires-Dist: moderngl
Requires-Dist: moderngl-window
Requires-Dist: numpy
Requires-Dist: pyglm
